filehero/__init__.py
filehero-0.1.0.dist-info/LICENSE
filehero-0.1.0.dist-info/METADATA
filehero-0.1.0.dist-info/WHEEL
filehero-0.1.0.dist-info/top_level.txt
filehero-0.1.0.dist-info/RECORD
