Metadata-Version: 2.1
Name: filehero
Version: 0.1.0
Summary: A file system utility lib.
Author-email: Alex Stevovich <alex.stevovich@gmail.com>
License: Copyright (c) 2017 Alex Stevovich
Classifier: Development Status :: 4 - Beta
Classifier: Intended Audience :: Developers
Classifier: License :: Other/Proprietary License
Classifier: Operating System :: OS Independent
Classifier: Programming Language :: Python :: 3
Classifier: Programming Language :: Python :: 3.8
Classifier: Programming Language :: Python :: 3.9
Classifier: Programming Language :: Python :: 3.10
License-File: LICENSE
